pytest_result_sender/__init__.py
pytest_result_sender/plugin.py
pytest_result_sender-0.1.1.dist-info/entry_points.txt
pytest_result_sender-0.1.1.dist-info/WHEEL
pytest_result_sender-0.1.1.dist-info/METADATA
pytest_result_sender-0.1.1.dist-info/RECORD
