Metadata-Version: 2.1
Name: pytest-result-sender
Version: 0.1.1
License: MIT
Author-email: dongfangtianyu <7629022+dongfangtianyu@users.noreply.github.com>
Requires-Python: >=3.10
Requires-Dist: pytest>=7.3.1
Requires-Dist: requests>=2.28.2
